pyoscope.py
readers.py
setup.py
PyOscope.egg-info/PKG-INFO
PyOscope.egg-info/SOURCES.txt
PyOscope.egg-info/dependency_links.txt
PyOscope.egg-info/requires.txt
PyOscope.egg-info/top_level.txt