Metadata-Version: 1.0
Name: PyOscope
Version: 1.0.1
Summary: Realtime plotter of data from files
Home-page: https://www.github.com/jlazear/pyoscope
Author: Justin Lazear
Author-email: jlazear@gmail.com
License: UNKNOWN
Platform: UNKNOWN
